pylibcucim/__init__.py
pylibcucim-0.0.0.dist-info/METADATA
pylibcucim-0.0.0.dist-info/WHEEL
pylibcucim-0.0.0.dist-info/top_level.txt
pylibcucim-0.0.0.dist-info/RECORD
